[
  {
    "id": 1,
    "title": "TechFest 2024 Highlights",
    "category": "Technical",
    "year": "2024–25",
    "event": "TechFest 2024",
    "description": "Students participating in coding competitions and exhibitions.",
    "imageUrl": "https://www.cryptopolitan.com/wp-content/uploads/2024/01/event-b192b9a9.webp"
  },
  {
    "id": 2,
    "title": "Cultural Dance Performance",
    "category": "Cultural",
    "year": "2024–25",
    "event": "Cultural Night 2024",
    "description": "Traditional dances performed by students.",
    "imageUrl": "https://userscontent2.emaze.com/images/7781358c-0c2c-4651-aa6c-534ec79b2d8b/5b50384d-122a-4e9b-8e71-9273821cb9d8.png"
  },
  {
    "id": 3,
    "title": "Project Exhibition Showcase",
    "category": "Technical",
    "year": "2024–25",
    "event": "TechFest 2024",
    "description": "Showcasing innovative student projects.",
    "imageUrl": "https://www.thetradeshownetwork.com/hubfs/rsna-1.jpg"
  },
  {
    "id": 4,
    "title": "Industry Tech Talk",
    "category": "Academic",
    "year": "2023–24",
    "event": "TechFest 2023",
    "description": "An expert sharing industry insights.",
    "imageUrl": "https://cdn.pressebox.de/a/34ceb15ef9e6209e/attachments/1233312.attachment/filename/827_2.jpg"
  },
  {
    "id": 5,
    "title": "Student Band Performance",
    "category": "Cultural",
    "year": "2024–25",
    "event": "Cultural Night 2024",
    "description": "Students performing live music.",
    "imageUrl": "https://music.northwestern.edu/sites/default/files/2018-11/concert_band.jpg"
  },
  {
    "id": 6,
    "title": "Drama Performance",
    "category": "Cultural",
    "year": "2022–23",
    "event": "Cultural Night 2022",
    "description": "Students performing a drama skit.",
    "imageUrl": "https://static01.nyt.com/images/2016/03/27/magazine/27shuffle-ss-slide-6K87/27shuffle-ss-slide-6K87-superJumbo.jpg"
  },
  {
    "id": 7,
    "title": "Inter-College Cricket Match",
    "category": "Sports",
    "year": "2022–23",
    "event": "Sports Meet 2022",
    "description": "Cricket tournament between colleges.",
    "imageUrl": "https://img.redbull.com/images/c_fill,g_auto,w_1200,h_630/f_auto,q_auto/redbullcom/2014/09/18/1331679348638_2/t20-batsmen-in-the-world-right-now"
  },
  {
    "id": 8,
    "title": "Track and Field Events",
    "category": "Sports",
    "year": "2023–24",
    "event": "Sports Meet 2023",
    "description": "Various track and field competitions.",
    "imageUrl": "https://4.bp.blogspot.com/-yMgIIzyBNnc/T_Ob_sbkuhI/AAAAAAAADEc/MGRA2xGq358/s1600/track%2Band%2Bfield%2Bday%2B2%2B3%2B1282.jpg"
  },
  {
    "id": 9,
    "title": "Basketball Tournament Finals",
    "category": "Sports",
    "year": "2022–23",
    "event": "Sports Meet 2022",
    "description": "Exciting basketball finals.",
    "imageUrl": "https://cdn.vox-cdn.com/thumbor/yLxlaTLbHy1d_tkihjeApT8cPQE=/0x0:4796x2698/1600x900/cdn.vox-cdn.com/uploads/chorus_image/image/53890687/657519570.0.jpg"
  },
  {
    "id": 10,
    "title": "Science Exhibition Display",
    "category": "Academic",
    "year": "2023–24",
    "event": "Science Exhibition 2023",
    "description": "Students presenting innovative science projects.",
    "imageUrl": "https://live.staticflickr.com/7075/7268714842_e7e3aa1829_b.jpg"
  },
  {
    "id": 11,
    "title": "Robotics Workshop",
    "category": "Technical",
    "year": "2023–24",
    "event": "Tech Workshop 2023",
    "description": "Hands-on robotics and automation workshop for students.",
    "imageUrl": "https://media.npr.org/assets/img/2023/10/04/mleong_scioly_20230831_slide-1fc39305d8ab464d47b44d973eec5ba99454c852.jpg"
  },
  {
    "id": 12,
    "title": "Annual Cultural Parade",
    "category": "Cultural",
    "year": "2023–24",
    "event": "Annual Day 2023",
    "description": "A parade showcasing student talents and cultural heritage.",
    "imageUrl": "https://img-s-msn-com.akamaized.net/tenant/amp/entityid/AA1xSK9q.img?w=940&h=529&m=4&q=74"
  },
  {
    "id": 13,
    "title": "Hackathon Challenge",
    "category": "Technical",
    "year": "2022–23",
    "event": "Hackathon 2022",
    "description": "Teams developing innovative solutions within 24 hours.",
    "imageUrl": "https://hightech.fm/wp-content/uploads/2023/09/41611db17477b9f54b70cec71260a4538800158cf1924e827bb2cfee028e9a87-2048x1152.jpeg"
  },
  {
    "id": 14,
    "title": "Guest Lecture on AI",
    "category": "Academic",
    "year": "2024–25",
    "event": "AI Summit 2024",
    "description": "Renowned professor delivering a lecture on artificial intelligence trends.",
    "imageUrl": "https://www.sueddeutsche.de/2022/06/14/23c5258b-714a-4ae1-b32d-d96964f4e482.jpeg?q=60&fm=jpeg&width=2000&rect=0%2C35%2C860%2C484"
  },
  {
    "id": 15,
    "title": "Chess Tournament",
    "category": "Sports",
    "year": "2023–24",
    "event": "Mind Sports 2023",
    "description": "Students competing in a strategic chess tournament.",
    "imageUrl": "https://images.squarespace-cdn.com/content/v1/54fe2721e4b03e430c530d7d/1696222503317-GUFQWPT4Z9KGIE0ID0KV/CFCC+2023+Autumn+Open+Tournament-1.jpg"
  },
  {
    "id": 16,
    "title": "Fashion Show",
    "category": "Cultural",
    "year": "2024–25",
    "event": "Cultural Night 2024",
    "description": "Showcasing modern and traditional student-designed outfits.",
    "imageUrl": "https://brechando.com/wp-content/uploads/2016/07/texo_moda-mariana-zappar.jpg"
  },
  {
    "id": 17,
    "title": "Coding Bootcamp",
    "category": "Technical",
    "year": "2023–24",
    "event": "Bootcamp 2023",
    "description": "Intensive programming sessions for beginners and enthusiasts.",
    "imageUrl": "https://wjccschools.org/nes/wp-content/uploads/sites/11/2019/11/IMG_6634-scaled.jpg"
  },
  {
    "id": 18,
    "title": "Mathematics Quiz",
    "category": "Academic",
    "year": "2022–23",
    "event": "Math Fest 2022",
    "description": "Inter-school mathematics quiz competition.",
    "imageUrl": "https://www.brookings.edu/wp-content/uploads/2017/04/es_20170426_understanding_and_addressing_teacher_shortages_in_us_dee_goldhaber.jpg"
  },
  {
    "id": 19,
    "title": "Football Championship",
    "category": "Sports",
    "year": "2024–25",
    "event": "Sports Meet 2024",
    "description": "Thrilling football matches between college teams.",
    "imageUrl": "https://www.americanfootballinternational.com/wp-content/uploads/Mexico-20223-ONEFA-Sept-16-Borregas-TEM-Tigres.png"
  },
  {
    "id": 20,
    "title": "Photography Exhibition",
    "category": "Cultural",
    "year": "2023–24",
    "event": "Art Fest 2023",
    "description": "Students displaying creative photography works.",
    "imageUrl": "https://www.studis-online.de/StudInfo/Bilder/HS/711-diploma-creative-direction1200x801.jpg"
  },
  {
    "id": 21,
    "title": "E-Sports Gaming Tournament",
    "category": "Sports",
    "year": "2024–25",
    "event": "E-Sports Fest 2024",
    "description": "Students competing in popular multiplayer video games.",
    "imageUrl": "https://upload.wikimedia.org/wikipedia/commons/thumb/c/c0/LOL2016WorldsFinalsArena.jpg/1600px-LOL2016WorldsFinalsArena.jpg"
  },
  {
    "id": 22,
    "title": "Debate Competition Finals",
    "category": "Academic",
    "year": "2023–24",
    "event": "Debate Fest 2023",
    "description": "Teams debating on current global issues.",
    "imageUrl": "https://upload.wikimedia.org/wikipedia/commons/thumb/f/fa/Debaters_compete_at_NSDA_Nationals_03.jpg/960px-Debaters_compete_at_NSDA_Nationals_03.jpg"
  },
  {
    "id": 23,
    "title": "Cultural Food Festival",
    "category": "Cultural",
    "year": "2022–23",
    "event": "Food Fest 2022",
    "description": "Students presenting traditional foods from different regions.",
    "imageUrl": "https://avatars.mds.yandex.net/get-altay/15112342/2a000001956b2137e9bcc833f19f27991090/XXXL"
  },
  {
    "id": 24,
    "title": "Drone Innovation Challenge",
    "category": "Technical",
    "year": "2024–25",
    "event": "TechFest 2024",
    "description": "Students designing and flying custom-built drones.",
    "imageUrl": "https://www.lockheedmartin.com/content/dam/lockheed-martin/eo/photo/news/events/alphapilot/austin-race/i-2PQpHmz-X4%20(1).jpg"
  },
  {
    "id": 25,
    "title": "Drama Theatre Night",
    "category": "Cultural",
    "year": "2023–24",
    "event": "Annual Day 2023",
    "description": "Stage performances of classic and modern plays.",
    "imageUrl": "https://static.tildacdn.com/tild3938-3564-4933-a165-643066653637/34.jpg"
  },
  {
    "id": 26,
    "title": "Cybersecurity Workshop",
    "category": "Technical",
    "year": "2022–23",
    "event": "CyberSec Summit 2022",
    "description": "Hands-on ethical hacking and cybersecurity awareness training.",
    "imageUrl": "https://www.esa.int/var/esa/storage/images/esa_multimedia/images/2023/05/civil_security_from_space/24895653-1-eng-GB/Civil_security_from_space.jpg"
  },
  {
    "id": 27,
    "title": "Poetry Recital Evening",
    "category": "Cultural",
    "year": "2024–25",
    "event": "Cultural Night 2024",
    "description": "Students performing self-written and classic poetry.",
    "imageUrl": "https://arc.stimg.co/startribunemedia/TCGHM2XWLUIZPJO72ZMF4TVVOU.jpg?&w=436&ar=3:2&fit=crop"
  },
  {
    "id": 28,
    "title": "Table Tennis Championship",
    "category": "Sports",
    "year": "2022–23",
    "event": "Sports Meet 2022",
    "description": "Fast-paced table tennis matches.",
    "imageUrl": "https://i.cbc.ca/1.5199621.1562246239!/fileImage/httpImage/youth-table-tennis-championship-summerside-2019.jpg"
  },
  {
    "id": 29,
    "title": "Astronomy Night",
    "category": "Academic",
    "year": "2024–25",
    "event": "Science Week 2024",
    "description": "Students exploring stars and planets with telescopes.",
    "imageUrl": "https://www.hannaplaut.com/wp-content/uploads/2023/03/mcdonald_observ_night-1536x1024.jpg"
  },
  {
    "id": 30,
    "title": "Start-Up Pitch Contest",
    "category": "Technical",
    "year": "2023–24",
    "event": "Innovation Week 2023",
    "description": "Student entrepreneurs presenting business ideas to judges.",
    "imageUrl": "https://www.sxsw.com/wp-content/uploads/2020/05/sxswpitch-Beverly-Schulze.png"
  },
  {
    "id": 31,
    "title": "Traditional Music Concert",
    "category": "Cultural",
    "year": "2023–24",
    "event": "Music Fest 2023",
    "description": "Live performance of cultural and folk instruments.",
    "imageUrl": "https://assets.classicfm.com/2014/27/springwood-high-school-concert-band7-1405022373-view-1.jpg"
  },
  {
    "id": 32,
    "title": "Badminton Open",
    "category": "Sports",
    "year": "2024–25",
    "event": "Sports Meet 2024",
    "description": "Badminton singles and doubles championship.",
    "imageUrl": "https://upload.wikimedia.org/wikipedia/commons/0/08/2011_US_Open_Badminton_2626.jpg"
  },
  {
    "id": 33,
    "title": "Literature Symposium",
    "category": "Academic",
    "year": "2022–23",
    "event": "LitFest 2022",
    "description": "Discussion panels and presentations on literature and language.",
    "imageUrl": "https://fmv.edu.tr/Uploads/Gallery/Medium/afdb64fd-8018-4dd0-a99d-779dd139fb1c.jpg"
  },
  {
    "id": 34,
    "title": "Coding Hack Sprint",
    "category": "Technical",
    "year": "2023–24",
    "event": "Hack Sprint 2023",
    "description": "Quick problem-solving coding competition.",
    "imageUrl": "https://miro.medium.com/v2/resize:fit:1200/1*ToKCG2zjVB12XFGBPYVVhg.png"
  },
  {
    "id": 35,
    "title": "Fine Arts Exhibition",
    "category": "Cultural",
    "year": "2022–23",
    "event": "Art Fest 2022",
    "description": "Students showcasing paintings, sculptures, and craftwork.",
    "imageUrl": "https://live.mts.ru/image/1300x1300/tretyakovskaya-galereya-zapustila-novii-tsifrovoi-proekt-caea0a74-1ec4-f4ed-faa2-ae693cf7387e.jpg"
  },
  {
    "id": 36,
    "title": "Robotics Race",
    "category": "Technical",
    "year": "2024–25",
    "event": "TechFest 2024",
    "description": "Students racing robots they have designed and built.",
    "imageUrl": "https://images.unian.net/photos/2016_10/thumb_files/1200_0_1477221540-8576.jpeg"
  },
  {
    "id": 37,
    "title": "Volleyball Cup Finals",
    "category": "Sports",
    "year": "2023–24",
    "event": "Sports Meet 2023",
    "description": "Exciting volleyball final match between top teams.",
    "imageUrl": "https://cdn.vox-cdn.com/thumbor/ObPkVJfnjLoqEKgxzTPCXe--5AY=/0x265:3688x2196/fit-in/1200x630/cdn.vox-cdn.com/uploads/chorus_asset/file/19552338/1189906066.jpg.jpg"
  },
  {
    "id": 38,
    "title": "Philosophy Discussion Forum",
    "category": "Academic",
    "year": "2024–25",
    "event": "Humanities Week 2024",
    "description": "Open dialogue on philosophy and critical thinking.",
    "imageUrl": "https://asset.library.wisc.edu/1711.dl/5YBS6WEY4CVY79D/M/h1380-08990.jpg"
  },
  {
    "id": 39,
    "title": "Martial Arts Demonstration",
    "category": "Sports",
    "year": "2022–23",
    "event": "Sports Meet 2022",
    "description": "Students demonstrating self-defense and martial art skills.",
    "imageUrl": "https://i.pinimg.com/originals/56/91/2c/56912c6c8aead6fb9cb276fa46739e4c.jpg"
  },
  {
    "id": 40,
    "title": "Cultural Fashion Parade",
    "category": "Cultural",
    "year": "2023–24",
    "event": "Cultural Night 2023",
    "description": "Runway show highlighting diverse cultural attire.",
    "imageUrl": "https://live.staticflickr.com/462/19027925970_6cc3fb8286_b.jpg"
  },
  {
    "id": 41,
    "title": "Environmental Awareness Rally",
    "category": "Academic",
    "year": "2024–25",
    "event": "Eco Week 2024",
    "description": "Students participating in a rally to promote environmental conservation.",
    "imageUrl": "https://live.staticflickr.com/6152/6194793172_34da979eb5_b.jpg"
  },
  {
    "id": 42,
    "title": "Alumni Meet and Greet",
    "category": "Cultural",
    "year": "2023–24",
    "event": "Alumni Reunion 2023",
    "description": "Current students and alumni connecting and sharing experiences.",
    "imageUrl": "https://parklandtalk.com/wp-content/uploads/2019/04/Lori-Alhadeff-meetgreet.jpg"
  }
]
